{"status": "Succeeded", "recognitionResult": {"lines": [{"boundingBox": [2855, 970, 2701, 2168, 2604, 2156, 2757, 957], "text": "25 058/560 well-marine-rot", "words": [{"boundingBox": [2853, 972, 2838, 1086, 2749, 1074, 2767, 960], "text": "25"}, {"boundingBox": [2833, 1118, 2782, 1520, 2688, 1509, 2745, 1107], "text": "058/560"}, {"boundingBox": [2779, 1540, 2704, 2164, 2610, 2154, 2685, 1529], "text": "well-marine-rot", "confidence": "Low"}]}, {"boundingBox": [2409, 1032, 2405, 1127, 2355, 1122, 2359, 1027], "text": "OU", "words": [{"boundingBox": [2408, 1047, 2404, 1126, 2354, 1124, 2358, 1045], "text": "OU", "confidence": "Low"}]}, {"boundingBox": [1382, 752, 1201, 1826, 1101, 1809, 1282, 735], "text": "95 716/360 welB-marine", "words": [{"boundingBox": [1379, 760, 1360, 881, 1261, 865, 1282, 744], "text": "95"}, {"boundingBox": [1354, 919, 1291, 1309, 1190, 1293, 1255, 903], "text": "716/360"}, {"boundingBox": [1286, 1335, 1198, 1822, 1105, 1807, 1185, 1319], "text": "welB-marine", "confidence": "Low"}]}, {"boundingBox": [944, 831, 928, 952, 858, 935, 879, 819], "text": "50", "words": [{"boundingBox": [944, 841, 929, 938, 859, 927, 874, 830], "text": "50"}]}]}}