{"status": "Succeeded", "recognitionResult": {"lines": [{"boundingBox": [981, 53, 1136, 52, 1136, 86, 982, 88], "text": "RABE", "words": [{"boundingBox": [984, 54, 1127, 52, 1128, 87, 985, 88], "text": "RABE"}]}, {"boundingBox": [1037, 92, 1085, 91, 1086, 106, 1038, 107], "text": "1920", "words": [{"boundingBox": [1038, 93, 1084, 92, 1084, 106, 1039, 107], "text": "1920"}]}, {"boundingBox": [83, 139, 161, 148, 158, 170, 80, 161], "text": "Shirt , ab", "words": [{"boundingBox": [83, 140, 115, 145, 115, 166, 83, 160], "text": "Shirt"}, {"boundingBox": [119, 146, 127, 146, 127, 167, 119, 166], "text": ","}, {"boundingBox": [131, 146, 156, 147, 156, 168, 131, 167], "text": "ab"}]}, {"boundingBox": [637, 135, 664, 139, 665, 162, 636, 157], "text": "shi", "words": [{"boundingBox": [641, 135, 667, 139, 663, 160, 637, 156], "text": "shi", "confidence": "Low"}]}, {"boundingBox": [78, 170, 174, 165, 174, 201, 80, 207], "text": "59,95", "words": [{"boundingBox": [85, 169, 171, 164, 173, 201, 87, 206], "text": "59,95", "confidence": "Low"}]}, {"boundingBox": [634, 168, 730, 164, 732, 198, 636, 205], "text": "49,95", "words": [{"boundingBox": [641, 167, 727, 162, 729, 199, 643, 204], "text": "49,95", "confidence": "Low"}]}, {"boundingBox": [83, 855, 103, 854, 103, 874, 83, 875], "text": "4", "words": [{"boundingBox": [84, 854, 97, 854, 98, 873, 85, 873], "text": "4"}]}, {"boundingBox": [84, 865, 159, 866, 158, 888, 83, 887], "text": "Shirt, ab", "words": [{"boundingBox": [84, 867, 127, 867, 128, 889, 85, 888], "text": "Shirt,"}, {"boundingBox": [131, 867, 157, 866, 158, 888, 132, 889], "text": "ab"}]}, {"boundingBox": [79, 891, 173, 887, 174, 921, 82, 930], "text": "59,95", "words": [{"boundingBox": [85, 890, 171, 884, 174, 923, 88, 929], "text": "59,95", "confidence": "Low"}]}, {"boundingBox": [976, 867, 1103, 866, 1104, 887, 977, 888], "text": "Sweatshirt, ab", "words": [{"boundingBox": [977, 869, 1073, 868, 1073, 888, 977, 887], "text": "Sweatshirt,"}, {"boundingBox": [1077, 868, 1100, 867, 1099, 888, 1076, 888], "text": "ab"}]}, {"boundingBox": [978, 891, 1065, 890, 1067, 922, 978, 929], "text": "79.95", "words": [{"boundingBox": [981, 890, 1064, 887, 1066, 924, 982, 927], "text": "79.95", "confidence": "Low"}]}, {"boundingBox": [82, 946, 192, 947, 191, 965, 81, 964], "text": "Material-Mix", "words": [{"boundingBox": [83, 947, 191, 947, 191, 965, 84, 963], "text": "Material-Mix"}]}, {"boundingBox": [82, 967, 168, 966, 169, 981, 83, 982], "text": "mit Spitze", "words": [{"boundingBox": [83, 968, 112, 968, 112, 982, 83, 982], "text": "mit"}, {"boundingBox": [115, 968, 162, 967, 163, 982, 115, 982], "text": "Spitze"}]}, {"boundingBox": [164, 1529, 629, 1527, 630, 1554, 165, 1557], "text": "MEHR INSPIRATION: www.mona.de/rabe", "words": [{"boundingBox": [166, 1533, 222, 1533, 222, 1554, 167, 1554], "text": "MEHR"}, {"boundingBox": [226, 1533, 352, 1531, 352, 1554, 226, 1554], "text": "INSPIRATION:"}, {"boundingBox": [356, 1531, 623, 1528, 623, 1555, 356, 1554], "text": "www.mona.de/rabe"}]}, {"boundingBox": [1082, 1529, 1133, 1528, 1133, 1553, 1082, 1554], "text": "19 D", "words": [{"boundingBox": [1083, 1528, 1111, 1528, 1111, 1553, 1083, 1553], "text": "19"}, {"boundingBox": [1116, 1528, 1131, 1528, 1131, 1553, 1116, 1553], "text": "D"}]}]}}