{"status": "Succeeded", "recognitionResult": {"lines": [{"boundingBox": [876, 42, 1130, 43, 1129, 64, 875, 62], "text": "1 Shirtjacke von RABE aus mehrfar-", "words": [{"boundingBox": [878, 42, 889, 42, 889, 63, 878, 63], "text": "1"}, {"boundingBox": [893, 42, 963, 44, 964, 63, 894, 63], "text": "Shirtjacke"}, {"boundingBox": [968, 44, 994, 44, 994, 63, 968, 63], "text": "von"}, {"boundingBox": [998, 44, 1035, 45, 1036, 63, 999, 63], "text": "RABE"}, {"boundingBox": [1039, 45, 1063, 45, 1064, 63, 1040, 63], "text": "aus"}, {"boundingBox": [1067, 45, 1129, 44, 1130, 63, 1068, 63], "text": "mehrfar-"}]}, {"boundingBox": [876, 64, 1109, 63, 1110, 81, 877, 82], "text": "bigen Effektgarnen in strukturierter", "words": [{"boundingBox": [877, 65, 915, 65, 915, 82, 878, 82], "text": "bigen"}, {"boundingBox": [919, 65, 1004, 65, 1003, 82, 919, 82], "text": "Effektgarnen"}, {"boundingBox": [1007, 65, 1022, 65, 1021, 82, 1007, 82], "text": "in"}, {"boundingBox": [1025, 65, 1109, 64, 1108, 83, 1025, 82], "text": "strukturierter"}]}, {"boundingBox": [878, 82, 1101, 84, 1100, 102, 877, 100], "text": "Boucle-Optik. Mit schimmernden", "words": [{"boundingBox": [878, 83, 965, 84, 966, 102, 878, 101], "text": "Boucle-Optik."}, {"boundingBox": [969, 84, 991, 84, 991, 102, 969, 102], "text": "Mit"}, {"boundingBox": [994, 84, 1099, 85, 1099, 102, 995, 102], "text": "schimmernden"}]}, {"boundingBox": [872, 102, 1109, 102, 1108, 122, 871, 121], "text": "Glanzgarn-Blenden und seitlichen", "words": [{"boundingBox": [876, 102, 1008, 103, 1008, 121, 876, 122], "text": "Glanzgarn-Blenden"}, {"boundingBox": [1012, 103, 1038, 103, 1038, 122, 1011, 121], "text": "und"}, {"boundingBox": [1042, 103, 1109, 103, 1109, 122, 1042, 122], "text": "seitlichen"}]}, {"boundingBox": [872, 123, 1089, 124, 1088, 142, 871, 141], "text": "Glanzgarn-Einsatzen. Verdeckte", "words": [{"boundingBox": [876, 124, 1019, 124, 1019, 142, 876, 142], "text": "Glanzgarn-Einsatzen."}, {"boundingBox": [1023, 124, 1088, 125, 1088, 142, 1023, 142], "text": "Verdeckte"}]}, {"boundingBox": [871, 141, 1127, 143, 1126, 162, 870, 161], "text": "Druckknopfleiste, lange Armel. Lange", "words": [{"boundingBox": [876, 143, 990, 144, 990, 161, 876, 160], "text": "Druckknopfleiste,"}, {"boundingBox": [993, 144, 1032, 144, 1033, 162, 994, 161], "text": "lange"}, {"boundingBox": [1036, 144, 1079, 144, 1080, 162, 1037, 162], "text": "Armel."}, {"boundingBox": [1082, 144, 1125, 143, 1126, 163, 1083, 162], "text": "Lange"}]}, {"boundingBox": [871, 162, 1132, 164, 1132, 183, 870, 181], "text": "in Gr. 38 ca. 60 cm. 49% Baumwolle,", "words": [{"boundingBox": [875, 164, 890, 164, 891, 181, 876, 181], "text": "in"}, {"boundingBox": [894, 164, 913, 164, 914, 181, 895, 181], "text": "Gr."}, {"boundingBox": [916, 164, 934, 164, 935, 181, 917, 181], "text": "38"}, {"boundingBox": [938, 164, 959, 164, 960, 181, 938, 181], "text": "ca."}, {"boundingBox": [962, 164, 980, 164, 981, 181, 963, 181], "text": "60"}, {"boundingBox": [984, 164, 1009, 164, 1010, 181, 984, 181], "text": "cm."}, {"boundingBox": [1013, 164, 1045, 164, 1046, 181, 1014, 181], "text": "49%"}, {"boundingBox": [1049, 164, 1131, 164, 1131, 183, 1049, 181], "text": "Baumwolle,"}]}, {"boundingBox": [875, 182, 1101, 182, 1101, 201, 876, 201], "text": "30% Viskose, 11% Polyester, 7%", "words": [{"boundingBox": [878, 183, 909, 184, 908, 200, 877, 200], "text": "30%"}, {"boundingBox": [912, 184, 968, 184, 967, 201, 911, 201], "text": "Viskose,"}, {"boundingBox": [971, 184, 1003, 184, 1002, 201, 971, 201], "text": "11%"}, {"boundingBox": [1006, 184, 1072, 183, 1072, 201, 1006, 201], "text": "Polyester,"}, {"boundingBox": [1075, 183, 1101, 182, 1100, 201, 1075, 201], "text": "7%"}]}, {"boundingBox": [874, 200, 1071, 202, 1070, 221, 873, 219], "text": "Polyacryl, 3% andere Fasern.", "words": [{"boundingBox": [876, 201, 941, 202, 941, 219, 876, 219], "text": "Polyacryl,"}, {"boundingBox": [945, 202, 968, 202, 968, 219, 945, 219], "text": "3%"}, {"boundingBox": [971, 202, 1019, 202, 1019, 220, 971, 219], "text": "andere"}, {"boundingBox": [1023, 202, 1071, 202, 1071, 221, 1023, 220], "text": "Fasern."}]}, {"boundingBox": [878, 221, 1008, 223, 1007, 241, 877, 239], "text": "Maschinenwasche.", "words": [{"boundingBox": [878, 222, 1008, 225, 1008, 240, 878, 240], "text": "Maschinenwasche."}]}, {"boundingBox": [879, 246, 1058, 247, 1058, 267, 878, 265], "text": "84 478/706 grau-flieder", "words": [{"boundingBox": [879, 247, 900, 247, 901, 265, 879, 265], "text": "84"}, {"boundingBox": [905, 247, 978, 247, 979, 266, 906, 265], "text": "478/706"}, {"boundingBox": [982, 247, 1057, 248, 1058, 267, 982, 266], "text": "grau-flieder"}]}, {"boundingBox": [877, 271, 924, 276, 924, 291, 876, 287], "text": "38. 40", "words": [{"boundingBox": [879, 270, 903, 272, 902, 288, 877, 286], "text": "38.", "confidence": "Low"}, {"boundingBox": [906, 273, 924, 274, 923, 290, 905, 289], "text": "40"}]}, {"boundingBox": [1079, 271, 1135, 272, 1134, 291, 1078, 289], "text": "139.95", "words": [{"boundingBox": [1082, 274, 1134, 274, 1135, 291, 1083, 291], "text": "139.95"}]}, {"boundingBox": [636, 290, 760, 291, 760, 316, 635, 315], "text": "Shirtjacke , ab", "words": [{"boundingBox": [638, 292, 719, 291, 719, 316, 638, 314], "text": "Shirtjacke"}, {"boundingBox": [724, 291, 731, 291, 731, 316, 724, 316], "text": ","}, {"boundingBox": [736, 291, 760, 291, 759, 316, 736, 316], "text": "ab"}]}, {"boundingBox": [877, 293, 947, 293, 947, 309, 878, 310], "text": "42, 44, 46", "words": [{"boundingBox": [878, 294, 901, 294, 902, 310, 878, 309], "text": "42,"}, {"boundingBox": [904, 294, 928, 294, 929, 310, 905, 310], "text": "44,"}, {"boundingBox": [931, 294, 946, 293, 947, 309, 932, 309], "text": "46"}]}, {"boundingBox": [1082, 292, 1136, 291, 1136, 309, 1083, 310], "text": "155.95", "words": [{"boundingBox": [1083, 292, 1137, 292, 1136, 309, 1083, 309], "text": "155.95"}]}, {"boundingBox": [641, 316, 756, 313, 755, 348, 643, 355], "text": "139.95", "words": [{"boundingBox": [645, 315, 754, 310, 756, 349, 647, 354], "text": "139.95", "confidence": "Low"}]}, {"boundingBox": [871, 312, 952, 311, 953, 329, 872, 330], "text": "48, 50, 52", "words": [{"boundingBox": [877, 313, 901, 314, 901, 330, 877, 330], "text": "48,"}, {"boundingBox": [904, 314, 928, 313, 928, 330, 904, 330], "text": "50,"}, {"boundingBox": [931, 313, 951, 312, 953, 329, 932, 330], "text": "52"}]}, {"boundingBox": [1081, 313, 1134, 312, 1135, 329, 1082, 330], "text": "169.95", "words": [{"boundingBox": [1083, 313, 1134, 313, 1135, 330, 1083, 330], "text": "169.95"}]}, {"boundingBox": [873, 349, 1120, 350, 1119, 370, 872, 368], "text": "2 Shirt von RABE. Im Vorderteil aus", "words": [{"boundingBox": [878, 349, 889, 349, 889, 370, 878, 370], "text": "2"}, {"boundingBox": [893, 350, 926, 351, 926, 370, 893, 370], "text": "Shirt"}, {"boundingBox": [930, 351, 956, 352, 956, 370, 930, 370], "text": "von"}, {"boundingBox": [960, 352, 1001, 352, 1001, 370, 960, 370], "text": "RABE."}, {"boundingBox": [1005, 352, 1023, 352, 1023, 370, 1005, 370], "text": "Im"}, {"boundingBox": [1027, 352, 1092, 352, 1092, 370, 1027, 370], "text": "Vorderteil"}, {"boundingBox": [1096, 352, 1120, 352, 1120, 370, 1096, 370], "text": "aus"}]}, {"boundingBox": [636, 379, 753, 380, 752, 401, 635, 400], "text": "Boucle-Optik", "words": [{"boundingBox": [638, 381, 751, 380, 751, 401, 638, 399], "text": "Boucle-Optik"}]}, {"boundingBox": [876, 369, 1112, 368, 1113, 385, 877, 386], "text": "duftigem Crepe gefertigt und floral", "words": [{"boundingBox": [879, 370, 934, 370, 934, 386, 879, 386], "text": "duftigem"}, {"boundingBox": [942, 370, 982, 370, 983, 385, 942, 386], "text": "Crepe"}, {"boundingBox": [986, 370, 1043, 370, 1043, 386, 986, 385], "text": "gefertigt"}, {"boundingBox": [1046, 370, 1074, 369, 1074, 386, 1046, 386], "text": "und"}, {"boundingBox": [1077, 369, 1114, 369, 1114, 386, 1077, 386], "text": "floral"}]}, {"boundingBox": [876, 388, 1102, 389, 1102, 409, 875, 407], "text": "bedruckt. Ruckteil und 3/4-lange", "words": [{"boundingBox": [876, 389, 938, 389, 939, 407, 877, 407], "text": "bedruckt."}, {"boundingBox": [942, 389, 996, 389, 996, 407, 942, 407], "text": "Ruckteil"}, {"boundingBox": [999, 389, 1027, 389, 1027, 408, 999, 407], "text": "und"}, {"boundingBox": [1030, 389, 1099, 390, 1100, 409, 1030, 408], "text": "3/4-lange"}]}, {"boundingBox": [876, 408, 1101, 410, 1101, 430, 875, 428], "text": "Armel aus meliertem Jersey. Ein", "words": [{"boundingBox": [877, 409, 917, 410, 916, 428, 876, 428], "text": "Armel"}, {"boundingBox": [921, 410, 944, 411, 943, 428, 920, 428], "text": "aus"}, {"boundingBox": [948, 411, 1017, 411, 1017, 429, 947, 428], "text": "meliertem"}, {"boundingBox": [1023, 411, 1068, 411, 1069, 429, 1023, 429], "text": "Jersey."}, {"boundingBox": [1072, 410, 1096, 410, 1097, 430, 1072, 429], "text": "Ein"}]}, {"boundingBox": [875, 429, 1102, 431, 1101, 449, 874, 447], "text": "Rippbundchen mit Glanzgarn am", "words": [{"boundingBox": [877, 430, 975, 432, 975, 448, 876, 447], "text": "Rippbundchen"}, {"boundingBox": [979, 432, 1003, 432, 1003, 448, 979, 448], "text": "mit"}, {"boundingBox": [1006, 432, 1078, 432, 1078, 449, 1006, 449], "text": "Glanzgarn"}, {"boundingBox": [1081, 432, 1100, 432, 1101, 449, 1082, 449], "text": "am"}]}, {"boundingBox": [877, 450, 1015, 453, 1014, 470, 876, 466], "text": "Ausschnitt setzt mod", "words": [{"boundingBox": [877, 451, 948, 452, 948, 468, 878, 467], "text": "Ausschnitt", "confidence": "Low"}, {"boundingBox": [951, 452, 983, 453, 984, 469, 952, 468], "text": "setzt", "confidence": "Low"}, {"boundingBox": [986, 453, 1014, 454, 1015, 470, 987, 469], "text": "mod"}]}, {"boundingBox": [872, 469, 1118, 470, 1117, 488, 871, 488], "text": "Mit Schulferpasse und elastischem", "words": [{"boundingBox": [875, 470, 898, 470, 898, 488, 876, 488], "text": "Mit"}, {"boundingBox": [902, 470, 997, 472, 997, 487, 902, 488], "text": "Schulferpasse", "confidence": "Low"}, {"boundingBox": [1001, 472, 1028, 472, 1029, 487, 1001, 487], "text": "und"}, {"boundingBox": [1032, 472, 1113, 471, 1113, 487, 1032, 487], "text": "elastischem"}]}, {"boundingBox": [874, 487, 1135, 486, 1136, 507, 875, 508], "text": "Saum. Lange in Gr. 38 ca. 64 cm. Jer-", "words": [{"boundingBox": [877, 488, 918, 488, 919, 507, 878, 508], "text": "Saum."}, {"boundingBox": [922, 488, 964, 488, 965, 507, 923, 507], "text": "Lange"}, {"boundingBox": [968, 488, 982, 488, 983, 507, 969, 507], "text": "in"}, {"boundingBox": [986, 488, 1005, 488, 1005, 507, 986, 507], "text": "Gr."}, {"boundingBox": [1009, 488, 1027, 488, 1027, 507, 1009, 507], "text": "38"}, {"boundingBox": [1030, 488, 1051, 487, 1051, 507, 1031, 507], "text": "ca."}, {"boundingBox": [1055, 487, 1074, 487, 1074, 507, 1055, 507], "text": "64"}, {"boundingBox": [1078, 487, 1103, 487, 1104, 507, 1078, 507], "text": "cm."}, {"boundingBox": [1107, 487, 1135, 487, 1135, 508, 1107, 507], "text": "Jer-"}]}, {"boundingBox": [875, 508, 1129, 507, 1130, 529, 876, 529], "text": "sey: 72% Viskose, 22% Polyester, 6%", "words": [{"boundingBox": [877, 509, 904, 509, 903, 528, 876, 529], "text": "sey:"}, {"boundingBox": [907, 509, 938, 509, 938, 528, 907, 528], "text": "72%"}, {"boundingBox": [942, 509, 997, 509, 997, 528, 942, 528], "text": "Viskose,"}, {"boundingBox": [1001, 509, 1033, 509, 1033, 528, 1001, 528], "text": "22%"}, {"boundingBox": [1036, 509, 1100, 508, 1101, 529, 1037, 528], "text": "Polyester,"}, {"boundingBox": [1104, 508, 1130, 508, 1130, 529, 1105, 529], "text": "6%"}]}, {"boundingBox": [877, 527, 1115, 529, 1114, 548, 876, 546], "text": "Elasthan. Vorderteil: 97% Polyester,", "words": [{"boundingBox": [877, 528, 938, 529, 938, 547, 877, 546], "text": "Elasthan."}, {"boundingBox": [941, 529, 1010, 530, 1010, 548, 941, 547], "text": "Vorderteil:"}, {"boundingBox": [1013, 530, 1046, 530, 1046, 548, 1014, 548], "text": "97%"}, {"boundingBox": [1049, 530, 1115, 529, 1115, 548, 1050, 548], "text": "Polyester,"}]}, {"boundingBox": [877, 548, 1098, 550, 1097, 567, 876, 566], "text": "3% Elasthan. Maschinenwasche.", "words": [{"boundingBox": [878, 549, 901, 549, 900, 567, 878, 566], "text": "3%"}, {"boundingBox": [904, 550, 966, 550, 966, 567, 904, 567], "text": "Elasthan."}, {"boundingBox": [970, 550, 1097, 550, 1098, 568, 970, 567], "text": "Maschinenwasche."}]}, {"boundingBox": [877, 571, 1058, 574, 1057, 594, 877, 592], "text": "49 053/006 grau-flieder", "words": [{"boundingBox": [878, 573, 901, 573, 900, 592, 877, 592], "text": "49"}, {"boundingBox": [905, 573, 977, 574, 977, 592, 904, 592], "text": "053/006"}, {"boundingBox": [981, 574, 1057, 576, 1057, 594, 981, 593], "text": "grau-flieder"}]}, {"boundingBox": [876, 597, 926, 600, 925, 617, 876, 615], "text": "38, 40", "words": [{"boundingBox": [878, 596, 902, 597, 901, 615, 877, 614], "text": "38,"}, {"boundingBox": [905, 597, 925, 598, 924, 616, 905, 615], "text": "40"}]}, {"boundingBox": [1085, 598, 1137, 599, 1136, 617, 1084, 616], "text": "59.95", "words": [{"boundingBox": [1090, 600, 1136, 600, 1137, 617, 1092, 617], "text": "59.95"}]}, {"boundingBox": [877, 617, 949, 620, 949, 638, 876, 635], "text": "42, 44, 46", "words": [{"boundingBox": [878, 618, 902, 619, 901, 636, 877, 635], "text": "42,"}, {"boundingBox": [905, 619, 929, 620, 929, 637, 905, 637], "text": "44,"}, {"boundingBox": [932, 620, 949, 620, 949, 638, 932, 638], "text": "46"}]}, {"boundingBox": [1086, 617, 1134, 616, 1135, 634, 1087, 635], "text": "65.95", "words": [{"boundingBox": [1090, 619, 1135, 618, 1134, 635, 1092, 635], "text": "65.95"}]}, {"boundingBox": [877, 638, 947, 639, 946, 655, 876, 654], "text": "48, 50, 52", "words": [{"boundingBox": [878, 639, 900, 639, 901, 655, 879, 655], "text": "48,"}, {"boundingBox": [903, 639, 928, 639, 929, 655, 904, 655], "text": "50,"}, {"boundingBox": [931, 639, 945, 639, 946, 655, 932, 655], "text": "52"}]}, {"boundingBox": [1089, 640, 1136, 640, 1135, 656, 1089, 656], "text": "69.95", "words": [{"boundingBox": [1092, 640, 1135, 640, 1135, 656, 1092, 656], "text": "69.95"}]}, {"boundingBox": [876, 674, 1109, 676, 1108, 695, 876, 694], "text": "3 Shirt von RABE mit raffiniertem", "words": [{"boundingBox": [878, 675, 890, 675, 889, 694, 878, 694], "text": "3"}, {"boundingBox": [893, 675, 926, 675, 926, 694, 893, 694], "text": "Shirt"}, {"boundingBox": [930, 675, 956, 676, 956, 694, 929, 694], "text": "von"}, {"boundingBox": [960, 676, 998, 676, 998, 694, 960, 694], "text": "RABE"}, {"boundingBox": [1002, 676, 1023, 677, 1023, 695, 1001, 694], "text": "mit"}, {"boundingBox": [1027, 677, 1104, 678, 1104, 695, 1027, 695], "text": "raffiniertem"}]}, {"boundingBox": [872, 696, 1081, 697, 1081, 715, 871, 714], "text": "Druckdessin in Ringeloptik mit", "words": [{"boundingBox": [876, 697, 959, 697, 959, 714, 875, 714], "text": "Druckdessin"}, {"boundingBox": [963, 697, 977, 697, 977, 714, 963, 714], "text": "in"}, {"boundingBox": [980, 697, 1057, 698, 1057, 715, 980, 714], "text": "Ringeloptik"}, {"boundingBox": [1061, 698, 1081, 698, 1081, 715, 1060, 715], "text": "mit"}]}, {"boundingBox": [870, 716, 1135, 716, 1135, 734, 871, 735], "text": "aufgedruckten Pailletten. Im Vorderteil", "words": [{"boundingBox": [876, 718, 975, 718, 975, 734, 876, 734], "text": "aufgedruckten"}, {"boundingBox": [978, 718, 1045, 717, 1045, 734, 979, 734], "text": "Pailletten."}, {"boundingBox": [1048, 717, 1063, 717, 1063, 734, 1048, 734], "text": "Im"}, {"boundingBox": [1069, 717, 1135, 716, 1135, 735, 1070, 734], "text": "Vorderteil"}]}, {"boundingBox": [870, 737, 1127, 736, 1128, 754, 871, 754], "text": "zusatzlich mit Farbverlauf, Floraldruck", "words": [{"boundingBox": [875, 738, 944, 738, 945, 753, 876, 754], "text": "zusatzlich"}, {"boundingBox": [947, 738, 970, 737, 971, 753, 948, 753], "text": "mit"}, {"boundingBox": [973, 737, 1053, 737, 1053, 753, 974, 753], "text": "Farbverlauf,"}, {"boundingBox": [1056, 737, 1128, 737, 1128, 755, 1056, 754], "text": "Floraldruck"}]}, {"boundingBox": [871, 757, 1126, 755, 1127, 773, 872, 774], "text": "und aufgestickten Pailletten im obe-", "words": [{"boundingBox": [876, 758, 904, 758, 904, 774, 876, 774], "text": "und"}, {"boundingBox": [907, 758, 998, 758, 999, 774, 907, 774], "text": "aufgestickten"}, {"boundingBox": [1002, 758, 1065, 757, 1065, 774, 1002, 774], "text": "Pailletten"}, {"boundingBox": [1068, 757, 1083, 757, 1084, 774, 1069, 774], "text": "im"}, {"boundingBox": [1091, 757, 1126, 756, 1127, 774, 1091, 774], "text": "obe-"}]}, {"boundingBox": [874, 775, 1109, 774, 1110, 793, 875, 794], "text": "ren Bereich. Lange in Gr. 38 ca. 64", "words": [{"boundingBox": [875, 776, 898, 776, 899, 794, 876, 795], "text": "ren"}, {"boundingBox": [901, 776, 956, 775, 957, 794, 902, 794], "text": "Bereich."}, {"boundingBox": [960, 775, 1002, 775, 1002, 794, 960, 794], "text": "Lange"}, {"boundingBox": [1006, 775, 1021, 775, 1021, 794, 1006, 794], "text": "in"}, {"boundingBox": [1024, 775, 1043, 775, 1043, 794, 1025, 794], "text": "Gr."}, {"boundingBox": [1047, 775, 1065, 775, 1065, 794, 1047, 794], "text": "38"}, {"boundingBox": [1069, 775, 1089, 775, 1089, 794, 1069, 794], "text": "ca."}, {"boundingBox": [1093, 775, 1110, 776, 1110, 794, 1092, 794], "text": "64"}]}, {"boundingBox": [876, 794, 1132, 795, 1131, 816, 875, 815], "text": "cm. Weicher Jersey aus 95% Viskose,", "words": [{"boundingBox": [876, 796, 900, 797, 900, 814, 877, 814], "text": "cm."}, {"boundingBox": [904, 797, 961, 797, 961, 814, 904, 814], "text": "Weicher"}, {"boundingBox": [965, 797, 1009, 797, 1009, 815, 965, 814], "text": "Jersey"}, {"boundingBox": [1013, 797, 1039, 797, 1039, 815, 1013, 815], "text": "aus"}, {"boundingBox": [1043, 797, 1074, 797, 1074, 816, 1043, 815], "text": "95%"}, {"boundingBox": [1077, 797, 1132, 795, 1133, 816, 1078, 816], "text": "Viskose,", "confidence": "Low"}]}, {"boundingBox": [877, 815, 1096, 817, 1095, 835, 877, 834], "text": "5% Elasthan. Maschinenwasche", "words": [{"boundingBox": [878, 816, 900, 817, 900, 834, 877, 834], "text": "5%"}, {"boundingBox": [904, 817, 966, 818, 965, 834, 903, 834], "text": "Elasthan."}, {"boundingBox": [969, 818, 1095, 819, 1096, 835, 969, 834], "text": "Maschinenwasche"}]}, {"boundingBox": [875, 838, 1060, 841, 1059, 860, 874, 857], "text": "35 334/006 flieder-grau", "words": [{"boundingBox": [877, 839, 900, 840, 900, 858, 878, 858], "text": "35"}, {"boundingBox": [905, 840, 977, 841, 978, 859, 905, 858], "text": "334/006"}, {"boundingBox": [981, 841, 1058, 842, 1059, 860, 981, 859], "text": "flieder-grau"}]}, {"boundingBox": [876, 864, 926, 867, 926, 883, 876, 881], "text": "38, 40", "words": [{"boundingBox": [879, 863, 903, 864, 902, 881, 878, 880], "text": "38,", "confidence": "Low"}, {"boundingBox": [906, 864, 925, 865, 924, 882, 905, 881], "text": "40"}]}, {"boundingBox": [1090, 864, 1135, 865, 1135, 882, 1090, 882], "text": "49.95", "words": [{"boundingBox": [1092, 863, 1134, 863, 1134, 881, 1092, 881], "text": "49.95"}]}, {"boundingBox": [876, 887, 954, 886, 955, 903, 877, 904], "text": "42, 44, 46", "words": [{"boundingBox": [878, 887, 902, 887, 901, 904, 877, 904], "text": "42,"}, {"boundingBox": [905, 887, 928, 887, 929, 904, 905, 904], "text": "44,"}, {"boundingBox": [932, 887, 952, 887, 954, 904, 932, 904], "text": "46"}]}, {"boundingBox": [1095, 886, 1135, 886, 1136, 903, 1095, 903], "text": "55.95", "words": [{"boundingBox": [1095, 886, 1135, 886, 1135, 903, 1095, 903], "text": "55.95", "confidence": "Low"}]}, {"boundingBox": [876, 902, 955, 905, 954, 923, 875, 921], "text": "48, 50, 52", "words": [{"boundingBox": [877, 903, 900, 904, 900, 922, 878, 921], "text": "48,"}, {"boundingBox": [904, 904, 927, 904, 927, 922, 903, 922], "text": "50,"}, {"boundingBox": [931, 905, 952, 905, 951, 923, 930, 922], "text": "52"}]}, {"boundingBox": [1090, 906, 1138, 906, 1138, 924, 1090, 923], "text": "59.95", "words": [{"boundingBox": [1091, 905, 1137, 905, 1137, 923, 1091, 923], "text": "59.95"}]}, {"boundingBox": [875, 940, 1127, 944, 1126, 964, 874, 960], "text": "4 Shirt von RABE in sportiver Ringe-", "words": [{"boundingBox": [878, 941, 889, 941, 889, 960, 878, 961], "text": "4"}, {"boundingBox": [893, 941, 927, 942, 926, 960, 893, 960], "text": "Shirt"}, {"boundingBox": [931, 942, 956, 943, 956, 960, 930, 960], "text": "von"}, {"boundingBox": [960, 943, 998, 943, 997, 960, 960, 960], "text": "RABE"}, {"boundingBox": [1002, 943, 1016, 943, 1015, 960, 1001, 960], "text": "in"}, {"boundingBox": [1020, 944, 1076, 944, 1076, 962, 1019, 960], "text": "sportiver"}, {"boundingBox": [1080, 944, 1127, 945, 1126, 964, 1079, 962], "text": "Ringe-"}]}, {"boundingBox": [876, 962, 1121, 964, 1121, 984, 875, 982], "text": "loptik. Die Web-Qualitativerderteil", "words": [{"boundingBox": [876, 963, 916, 963, 916, 981, 876, 981], "text": "loptik."}, {"boundingBox": [920, 963, 942, 964, 941, 981, 919, 981], "text": "Die"}, {"boundingBox": [946, 964, 1121, 964, 1121, 984, 945, 981], "text": "Web-Qualitativerderteil", "confidence": "Low"}]}, {"boundingBox": [870, 984, 1120, 983, 1121, 1002, 871, 1002], "text": "ist zusatzlich mit einem farbharmo-", "words": [{"boundingBox": [875, 985, 892, 985, 892, 1002, 875, 1002], "text": "ist"}, {"boundingBox": [895, 985, 964, 986, 964, 1002, 896, 1002], "text": "zusatzlich"}, {"boundingBox": [967, 986, 990, 986, 991, 1002, 968, 1002], "text": "mit"}, {"boundingBox": [994, 986, 1033, 986, 1034, 1002, 994, 1002], "text": "einem"}, {"boundingBox": [1040, 986, 1119, 984, 1120, 1002, 1041, 1002], "text": "farbharmo-"}]}, {"boundingBox": [870, 1004, 1122, 1003, 1123, 1021, 871, 1021], "text": "nischen Blumendessin bedruckf und", "words": [{"boundingBox": [876, 1005, 930, 1005, 931, 1021, 876, 1022], "text": "nischen"}, {"boundingBox": [934, 1005, 1031, 1005, 1031, 1021, 934, 1021], "text": "Blumendessin"}, {"boundingBox": [1034, 1005, 1094, 1005, 1095, 1021, 1035, 1021], "text": "bedruckf", "confidence": "Low"}, {"boundingBox": [1098, 1005, 1121, 1004, 1122, 1022, 1098, 1021], "text": "und"}]}, {"boundingBox": [876, 1025, 1123, 1023, 1124, 1041, 877, 1042], "text": "mit funkeindem Strass besetzt. Ruck-", "words": [{"boundingBox": [878, 1025, 898, 1025, 897, 1042, 877, 1042], "text": "mit"}, {"boundingBox": [901, 1025, 981, 1026, 980, 1042, 901, 1042], "text": "funkeindem", "confidence": "Low"}, {"boundingBox": [987, 1026, 1028, 1026, 1028, 1041, 987, 1042], "text": "Strass"}, {"boundingBox": [1032, 1026, 1084, 1025, 1084, 1041, 1031, 1041], "text": "besetzt.", "confidence": "Low"}, {"boundingBox": [1087, 1025, 1123, 1025, 1123, 1041, 1087, 1041], "text": "Ruck-"}]}, {"boundingBox": [879, 1042, 1122, 1043, 1121, 1062, 878, 1061], "text": "eil und 3/4-lange Armel aus Jersey.", "words": [{"boundingBox": [880, 1044, 897, 1043, 898, 1061, 881, 1061], "text": "eil"}, {"boundingBox": [901, 1043, 929, 1043, 930, 1060, 901, 1060], "text": "und"}, {"boundingBox": [933, 1043, 998, 1043, 998, 1060, 933, 1060], "text": "3/4-lange"}, {"boundingBox": [1001, 1043, 1041, 1043, 1041, 1060, 1001, 1060], "text": "Armel"}, {"boundingBox": [1045, 1043, 1071, 1043, 1071, 1061, 1044, 1060], "text": "aus"}, {"boundingBox": [1074, 1043, 1121, 1044, 1121, 1062, 1074, 1061], "text": "Jersey."}]}, {"boundingBox": [876, 1060, 1121, 1063, 1120, 1082, 875, 1079], "text": "Schulter- und Ruckenpasse sind mit", "words": [{"boundingBox": [878, 1061, 937, 1062, 937, 1081, 878, 1080], "text": "Schulter-"}, {"boundingBox": [940, 1062, 967, 1062, 968, 1081, 940, 1081], "text": "und"}, {"boundingBox": [971, 1062, 1062, 1063, 1062, 1082, 971, 1081], "text": "Ruckenpasse"}, {"boundingBox": [1066, 1063, 1094, 1063, 1094, 1082, 1066, 1082], "text": "sind"}, {"boundingBox": [1098, 1063, 1122, 1063, 1122, 1083, 1098, 1082], "text": "mit"}]}, {"boundingBox": [556, 1098, 644, 1099, 643, 1121, 555, 1120], "text": "Shirtjacke", "words": [{"boundingBox": [559, 1099, 643, 1099, 642, 1121, 559, 1121], "text": "Shirtjacke"}]}, {"boundingBox": [877, 1080, 1133, 1082, 1133, 1104, 876, 1102], "text": "Spitze gedoppelt, den Ausschnitt ziert", "words": [{"boundingBox": [878, 1082, 918, 1083, 918, 1101, 877, 1102], "text": "Spitze"}, {"boundingBox": [922, 1083, 997, 1084, 997, 1102, 922, 1101], "text": "gedoppelt,"}, {"boundingBox": [1001, 1084, 1024, 1084, 1024, 1102, 1001, 1102], "text": "den"}, {"boundingBox": [1028, 1084, 1098, 1083, 1098, 1103, 1028, 1102], "text": "Ausschnitt"}, {"boundingBox": [1102, 1083, 1133, 1082, 1133, 1104, 1101, 1103], "text": "ziert"}]}, {"boundingBox": [873, 1101, 1130, 1102, 1130, 1122, 872, 1121], "text": "ein kleiner Schlitz. Lange in Gr. 38 ca.", "words": [{"boundingBox": [876, 1103, 897, 1103, 898, 1120, 876, 1120], "text": "ein"}, {"boundingBox": [901, 1103, 948, 1103, 948, 1120, 902, 1120], "text": "kleiner"}, {"boundingBox": [951, 1103, 998, 1103, 999, 1120, 952, 1120], "text": "Schlitz."}, {"boundingBox": [1002, 1103, 1044, 1103, 1045, 1121, 1002, 1120], "text": "Lange"}, {"boundingBox": [1048, 1103, 1063, 1103, 1063, 1121, 1048, 1121], "text": "in"}, {"boundingBox": [1066, 1103, 1085, 1103, 1086, 1122, 1066, 1121], "text": "Gr."}, {"boundingBox": [1089, 1103, 1107, 1102, 1107, 1122, 1089, 1122], "text": "38"}, {"boundingBox": [1111, 1102, 1129, 1102, 1129, 1123, 1111, 1122], "text": "ca."}]}, {"boundingBox": [877, 1120, 1114, 1122, 1114, 1142, 876, 1140], "text": "62 cm. 96% Viskose, 4% Elasthan,", "words": [{"boundingBox": [877, 1122, 896, 1122, 896, 1140, 878, 1140], "text": "62"}, {"boundingBox": [899, 1122, 925, 1122, 926, 1140, 900, 1140], "text": "cm."}, {"boundingBox": [928, 1122, 959, 1122, 960, 1140, 929, 1140], "text": "96%"}, {"boundingBox": [963, 1122, 1019, 1122, 1019, 1140, 963, 1140], "text": "Viskose,"}, {"boundingBox": [1022, 1122, 1045, 1122, 1046, 1140, 1023, 1140], "text": "4%"}, {"boundingBox": [1049, 1122, 1114, 1122, 1114, 1142, 1050, 1140], "text": "Elasthan,"}]}, {"boundingBox": [878, 1142, 1122, 1141, 1122, 1160, 879, 1161], "text": "Spitze: 100% Polyester. Maschinen-", "words": [{"boundingBox": [879, 1143, 923, 1143, 923, 1160, 879, 1160], "text": "Spitze:"}, {"boundingBox": [927, 1143, 967, 1143, 967, 1160, 926, 1160], "text": "100%"}, {"boundingBox": [971, 1143, 1034, 1143, 1033, 1161, 970, 1160], "text": "Polyester."}, {"boundingBox": [1037, 1143, 1122, 1142, 1121, 1162, 1037, 1161], "text": "Maschinen-"}]}, {"boundingBox": [874, 1160, 931, 1163, 930, 1181, 873, 1178], "text": "wasche.", "words": [{"boundingBox": [876, 1162, 930, 1164, 930, 1181, 876, 1179], "text": "wasche."}]}, {"boundingBox": [877, 1185, 1058, 1188, 1057, 1207, 876, 1204], "text": "91 823/306 grau-flieder", "words": [{"boundingBox": [877, 1186, 901, 1186, 902, 1204, 877, 1204], "text": "91"}, {"boundingBox": [905, 1186, 978, 1188, 978, 1206, 905, 1205], "text": "823/306"}, {"boundingBox": [981, 1188, 1058, 1189, 1058, 1207, 982, 1206], "text": "grau-flieder"}]}, {"boundingBox": [875, 1210, 926, 1213, 926, 1229, 876, 1228], "text": "38, 40", "words": [{"boundingBox": [878, 1210, 902, 1211, 901, 1229, 877, 1228], "text": "38,"}, {"boundingBox": [906, 1211, 925, 1211, 924, 1229, 905, 1229], "text": "40"}]}, {"boundingBox": [1087, 1212, 1137, 1213, 1136, 1229, 1086, 1228], "text": "59.95", "words": [{"boundingBox": [1090, 1213, 1134, 1213, 1135, 1228, 1092, 1229], "text": "59.95"}]}, {"boundingBox": [878, 1231, 950, 1232, 949, 1249, 877, 1248], "text": "42, 44, 46", "words": [{"boundingBox": [878, 1232, 900, 1232, 901, 1249, 878, 1249], "text": "42,"}, {"boundingBox": [904, 1232, 927, 1232, 927, 1249, 904, 1249], "text": "44,"}, {"boundingBox": [930, 1232, 949, 1232, 950, 1249, 931, 1249], "text": "46"}]}, {"boundingBox": [1088, 1233, 1132, 1231, 1133, 1248, 1089, 1249], "text": "65,95", "words": [{"boundingBox": [1090, 1231, 1131, 1230, 1132, 1247, 1091, 1248], "text": "65,95", "confidence": "Low"}]}, {"boundingBox": [877, 1252, 925, 1253, 926, 1269, 876, 1269], "text": "48, 50", "words": [{"boundingBox": [878, 1251, 902, 1251, 901, 1268, 878, 1268], "text": "48,"}, {"boundingBox": [905, 1251, 925, 1251, 925, 1268, 905, 1268], "text": "50"}]}, {"boundingBox": [1096, 1252, 1135, 1252, 1135, 1269, 1096, 1269], "text": "9.95", "words": [{"boundingBox": [1101, 1252, 1134, 1252, 1134, 1269, 1101, 1269], "text": "9.95"}]}, {"boundingBox": [878, 1285, 1108, 1288, 1107, 1309, 877, 1306], "text": "5 Sweatshirt von RABE mit effekt-", "words": [{"boundingBox": [879, 1286, 889, 1287, 889, 1306, 878, 1306], "text": "5"}, {"boundingBox": [893, 1287, 967, 1290, 967, 1307, 893, 1307], "text": "Sweatshirt"}, {"boundingBox": [971, 1290, 998, 1290, 998, 1307, 971, 1307], "text": "von"}, {"boundingBox": [1002, 1290, 1039, 1290, 1039, 1308, 1002, 1308], "text": "RABE"}, {"boundingBox": [1043, 1290, 1065, 1290, 1066, 1309, 1043, 1308], "text": "mit", "confidence": "Low"}, {"boundingBox": [1069, 1290, 1108, 1289, 1108, 1309, 1070, 1309], "text": "effekt-"}]}, {"boundingBox": [875, 1309, 1103, 1310, 1102, 1327, 874, 1326], "text": "starker Stuktur und abnehmbarer", "words": [{"boundingBox": [877, 1310, 923, 1311, 922, 1327, 876, 1326], "text": "starker"}, {"boundingBox": [926, 1311, 974, 1312, 974, 1327, 925, 1327], "text": "Stuktur"}, {"boundingBox": [977, 1312, 1004, 1312, 1004, 1327, 977, 1327], "text": "und"}, {"boundingBox": [1007, 1312, 1102, 1311, 1103, 1327, 1008, 1327], "text": "abnehmbarer"}]}, {"boundingBox": [877, 1329, 1122, 1328, 1123, 1347, 878, 1348], "text": "Strass-Brosche. Schimmernde Nahte", "words": [{"boundingBox": [878, 1330, 979, 1330, 980, 1348, 878, 1348], "text": "Strass-Brosche."}, {"boundingBox": [983, 1330, 1078, 1329, 1078, 1348, 983, 1348], "text": "Schimmernde"}, {"boundingBox": [1082, 1329, 1123, 1329, 1123, 1349, 1082, 1348], "text": "Nahte"}]}, {"boundingBox": [875, 1349, 1127, 1350, 1127, 1368, 874, 1368], "text": "aus Glanzgarn am Ausschnitt und an", "words": [{"boundingBox": [876, 1350, 901, 1350, 902, 1368, 876, 1368], "text": "aus"}, {"boundingBox": [905, 1350, 976, 1351, 977, 1368, 905, 1368], "text": "Glanzgarn"}, {"boundingBox": [980, 1351, 1001, 1351, 1001, 1368, 980, 1368], "text": "am"}, {"boundingBox": [1004, 1351, 1075, 1350, 1076, 1368, 1005, 1368], "text": "Ausschnitt"}, {"boundingBox": [1079, 1350, 1106, 1350, 1107, 1368, 1080, 1368], "text": "und"}, {"boundingBox": [1109, 1350, 1125, 1350, 1126, 1368, 1110, 1368], "text": "an"}]}, {"boundingBox": [877, 1369, 1123, 1367, 1124, 1386, 878, 1388], "text": "den geschlitzten 3/4-Armel. Mit Sei-", "words": [{"boundingBox": [879, 1371, 904, 1371, 904, 1388, 879, 1388], "text": "den"}, {"boundingBox": [907, 1371, 991, 1370, 991, 1387, 907, 1388], "text": "geschlitzten"}, {"boundingBox": [994, 1370, 1064, 1369, 1064, 1387, 994, 1387], "text": "3/4-Armel."}, {"boundingBox": [1067, 1369, 1089, 1368, 1090, 1387, 1067, 1387], "text": "Mit"}, {"boundingBox": [1092, 1368, 1124, 1368, 1124, 1388, 1093, 1387], "text": "Sei-"}]}, {"boundingBox": [878, 1388, 1114, 1389, 1114, 1408, 877, 1407], "text": "tenschlitzen. Lange in Gr. 38 ca. 60", "words": [{"boundingBox": [878, 1390, 962, 1390, 962, 1407, 878, 1406], "text": "tenschlitzen.", "confidence": "Low"}, {"boundingBox": [965, 1390, 1007, 1390, 1008, 1407, 965, 1407], "text": "Lange"}, {"boundingBox": [1011, 1390, 1025, 1390, 1026, 1407, 1011, 1407], "text": "in"}, {"boundingBox": [1029, 1390, 1049, 1390, 1049, 1407, 1029, 1407], "text": "Gr."}, {"boundingBox": [1052, 1390, 1070, 1390, 1071, 1408, 1053, 1407], "text": "38"}, {"boundingBox": [1073, 1390, 1093, 1389, 1094, 1408, 1074, 1408], "text": "ca."}, {"boundingBox": [1097, 1389, 1114, 1389, 1114, 1408, 1097, 1408], "text": "60"}]}, {"boundingBox": [875, 1408, 1114, 1409, 1114, 1427, 874, 1426], "text": "cm. 92% Baumwolle, 8% Elasthan.", "words": [{"boundingBox": [877, 1409, 902, 1410, 902, 1426, 877, 1426], "text": "cm."}, {"boundingBox": [905, 1410, 938, 1410, 939, 1426, 905, 1426], "text": "92%"}, {"boundingBox": [942, 1410, 1021, 1410, 1021, 1427, 942, 1426], "text": "Baumwolle,"}, {"boundingBox": [1024, 1410, 1047, 1410, 1048, 1427, 1025, 1427], "text": "8%"}, {"boundingBox": [1051, 1410, 1114, 1409, 1114, 1427, 1051, 1427], "text": "Elasthan."}]}, {"boundingBox": [873, 1427, 1004, 1429, 1003, 1448, 872, 1446], "text": "Maschinenwasche", "words": [{"boundingBox": [875, 1428, 1004, 1431, 1004, 1447, 876, 1447], "text": "Maschinenwasche"}]}, {"boundingBox": [873, 1452, 1025, 1453, 1025, 1473, 872, 1472], "text": "66 028/006 flieder", "words": [{"boundingBox": [877, 1454, 899, 1453, 900, 1472, 877, 1472], "text": "66"}, {"boundingBox": [904, 1453, 977, 1453, 977, 1472, 905, 1472], "text": "028/006"}, {"boundingBox": [981, 1453, 1025, 1454, 1025, 1473, 981, 1472], "text": "flieder"}]}, {"boundingBox": [876, 1478, 929, 1480, 929, 1495, 876, 1496], "text": "38, 40", "words": [{"boundingBox": [878, 1477, 902, 1477, 902, 1495, 878, 1495], "text": "38,"}, {"boundingBox": [905, 1477, 926, 1477, 926, 1495, 905, 1495], "text": "40"}]}, {"boundingBox": [1084, 1479, 1134, 1479, 1134, 1496, 1085, 1496], "text": "79.95", "words": [{"boundingBox": [1093, 1479, 1133, 1479, 1133, 1496, 1093, 1496], "text": "79.95"}]}, {"boundingBox": [873, 1495, 951, 1499, 950, 1516, 872, 1512], "text": "42. 44, 46", "words": [{"boundingBox": [877, 1496, 902, 1497, 902, 1514, 878, 1513], "text": "42.", "confidence": "Low"}, {"boundingBox": [905, 1497, 928, 1498, 928, 1515, 905, 1515], "text": "44,"}, {"boundingBox": [931, 1498, 951, 1499, 951, 1516, 931, 1515], "text": "46"}]}, {"boundingBox": [1089, 1497, 1137, 1499, 1136, 1518, 1090, 1515], "text": "89.95", "words": [{"boundingBox": [1092, 1496, 1135, 1498, 1134, 1517, 1091, 1515], "text": "89.95"}]}, {"boundingBox": [876, 1516, 954, 1518, 953, 1537, 875, 1535], "text": "48, 50, 52", "words": [{"boundingBox": [878, 1517, 901, 1518, 900, 1537, 877, 1535], "text": "48,"}, {"boundingBox": [905, 1518, 928, 1519, 927, 1537, 904, 1537], "text": "50,"}, {"boundingBox": [932, 1519, 954, 1518, 953, 1537, 931, 1537], "text": "52"}]}, {"boundingBox": [1089, 1516, 1138, 1518, 1138, 1537, 1089, 1535], "text": "99.95", "words": [{"boundingBox": [1091, 1516, 1137, 1517, 1136, 1536, 1090, 1535], "text": "99.95"}]}, {"boundingBox": [43, 1531, 70, 1530, 71, 1552, 43, 1553], "text": "18", "words": [{"boundingBox": [45, 1529, 69, 1529, 70, 1551, 46, 1552], "text": "18"}]}]}}