{"status": "Succeeded", "recognitionResult": {"lines": [{"boundingBox": [640, 112, 964, 114, 963, 137, 640, 136], "text": "1 Pullover von delmod. Ein Kombi-Partner, der", "words": [{"boundingBox": [646, 113, 654, 113, 654, 136, 645, 136], "text": "1"}, {"boundingBox": [659, 113, 717, 114, 716, 136, 658, 136], "text": "Pullover"}, {"boundingBox": [721, 114, 748, 114, 747, 136, 721, 136], "text": "von"}, {"boundingBox": [752, 114, 809, 115, 808, 136, 752, 136], "text": "delmod."}, {"boundingBox": [813, 115, 834, 115, 834, 136, 813, 136], "text": "Ein"}, {"boundingBox": [839, 115, 938, 116, 938, 136, 838, 136], "text": "Kombi-Partner,"}, {"boundingBox": [943, 116, 963, 116, 963, 137, 942, 136], "text": "der"}]}, {"boundingBox": [644, 135, 994, 136, 993, 156, 643, 155], "text": "sich durch die besonders hautfreundliche und edle", "words": [{"boundingBox": [645, 136, 673, 136, 672, 155, 644, 155], "text": "sich"}, {"boundingBox": [677, 136, 716, 136, 716, 155, 676, 155], "text": "durch"}, {"boundingBox": [720, 136, 739, 136, 739, 155, 719, 155], "text": "die"}, {"boundingBox": [743, 136, 814, 136, 814, 155, 742, 155], "text": "besonders"}, {"boundingBox": [817, 136, 925, 136, 926, 156, 817, 155], "text": "hautfreundliche"}, {"boundingBox": [929, 136, 957, 136, 957, 156, 929, 156], "text": "und"}, {"boundingBox": [961, 136, 992, 136, 993, 156, 961, 156], "text": "edle"}]}, {"boundingBox": [643, 156, 978, 156, 977, 175, 642, 174], "text": "Garnmischung auszeichnet. In gerader Form, mit", "words": [{"boundingBox": [643, 156, 743, 158, 744, 175, 643, 175], "text": "Garnmischung"}, {"boundingBox": [747, 158, 832, 158, 833, 175, 747, 175], "text": "auszeichnet."}, {"boundingBox": [836, 158, 850, 158, 851, 175, 837, 175], "text": "In"}, {"boundingBox": [854, 158, 906, 157, 907, 175, 855, 175], "text": "gerader"}, {"boundingBox": [909, 157, 948, 157, 949, 175, 910, 175], "text": "Form,"}, {"boundingBox": [951, 157, 977, 157, 978, 175, 953, 175], "text": "mit"}]}, {"boundingBox": [41, 178, 147, 181, 146, 205, 40, 202], "text": "Pullover, ab", "words": [{"boundingBox": [41, 181, 117, 181, 117, 205, 42, 202], "text": "Pullover,"}, {"boundingBox": [121, 181, 147, 181, 146, 205, 121, 205], "text": "ab"}]}, {"boundingBox": [638, 176, 965, 177, 964, 195, 637, 194], "text": "Rippenabschlussen. Lange in Gr. 38 ca. 63 cm.", "words": [{"boundingBox": [641, 177, 778, 177, 779, 195, 642, 195], "text": "Rippenabschlussen."}, {"boundingBox": [782, 177, 824, 177, 825, 195, 782, 195], "text": "Lange"}, {"boundingBox": [828, 177, 842, 177, 843, 195, 829, 195], "text": "in"}, {"boundingBox": [846, 177, 865, 177, 865, 195, 846, 195], "text": "Gr."}, {"boundingBox": [868, 177, 886, 177, 887, 195, 869, 195], "text": "38"}, {"boundingBox": [890, 177, 910, 177, 911, 195, 890, 195], "text": "ca."}, {"boundingBox": [914, 177, 933, 177, 933, 195, 914, 195], "text": "63"}, {"boundingBox": [936, 177, 963, 177, 964, 196, 937, 195], "text": "cm."}]}, {"boundingBox": [39, 211, 132, 205, 131, 240, 40, 246], "text": "69.99", "words": [{"boundingBox": [42, 210, 130, 204, 133, 239, 44, 245], "text": "69.99", "confidence": "Low"}]}, {"boundingBox": [644, 194, 994, 195, 993, 215, 643, 214], "text": "Feinstrick aus 90% Baumwolle und 10% Kaschmir.", "words": [{"boundingBox": [644, 195, 706, 195, 707, 214, 645, 214], "text": "Feinstrick"}, {"boundingBox": [710, 195, 736, 195, 736, 214, 710, 214], "text": "aus"}, {"boundingBox": [740, 195, 772, 195, 772, 215, 740, 214], "text": "90%"}, {"boundingBox": [775, 195, 852, 195, 852, 215, 776, 215], "text": "Baumwolle"}, {"boundingBox": [856, 195, 884, 195, 884, 215, 856, 215], "text": "und"}, {"boundingBox": [888, 195, 919, 195, 919, 216, 888, 215], "text": "10%"}, {"boundingBox": [923, 195, 994, 195, 994, 216, 923, 216], "text": "Kaschmir."}]}, {"boundingBox": [640, 213, 777, 216, 776, 236, 639, 232], "text": "Maschinenwasche.", "words": [{"boundingBox": [642, 214, 776, 218, 775, 235, 642, 233], "text": "Maschinenwasche."}]}, {"boundingBox": [643, 237, 797, 240, 796, 259, 642, 256], "text": "25 146/806 koralle", "words": [{"boundingBox": [643, 239, 665, 239, 666, 257, 644, 257], "text": "25"}, {"boundingBox": [673, 239, 743, 240, 744, 258, 673, 257], "text": "146/806"}, {"boundingBox": [747, 240, 795, 241, 796, 260, 748, 258], "text": "koralle"}]}, {"boundingBox": [41, 262, 55, 260, 56, 276, 42, 279], "text": "3", "words": [{"boundingBox": [41, 261, 52, 259, 55, 275, 44, 277], "text": "3"}]}, {"boundingBox": [38, 277, 144, 279, 144, 300, 37, 298], "text": "Hemdbluse", "words": [{"boundingBox": [41, 279, 140, 279, 140, 300, 41, 298], "text": "Hemdbluse"}]}, {"boundingBox": [639, 264, 698, 267, 697, 285, 638, 282], "text": "38, 40", "words": [{"boundingBox": [642, 265, 667, 266, 668, 283, 644, 283], "text": "38,"}, {"boundingBox": [671, 266, 691, 267, 692, 284, 671, 283], "text": "40"}]}, {"boundingBox": [953, 266, 996, 265, 996, 282, 954, 282], "text": "69.99", "words": [{"boundingBox": [955, 264, 994, 264, 994, 281, 955, 281], "text": "69.99", "confidence": "Low"}]}, {"boundingBox": [643, 284, 716, 287, 715, 305, 642, 303], "text": "42, 44, 46", "words": [{"boundingBox": [643, 285, 667, 286, 668, 304, 644, 303], "text": "42,"}, {"boundingBox": [671, 286, 693, 287, 694, 304, 671, 304], "text": "44,"}, {"boundingBox": [697, 287, 715, 287, 716, 304, 698, 304], "text": "46"}]}, {"boundingBox": [950, 285, 995, 284, 996, 303, 951, 303], "text": "75.99", "words": [{"boundingBox": [956, 283, 995, 283, 995, 302, 956, 302], "text": "75.99"}]}, {"boundingBox": [642, 304, 720, 306, 719, 324, 641, 322], "text": "48, 50, 52", "words": [{"boundingBox": [644, 305, 667, 306, 667, 323, 644, 322], "text": "48,"}, {"boundingBox": [670, 306, 694, 306, 695, 324, 670, 323], "text": "50,"}, {"boundingBox": [697, 306, 717, 307, 718, 324, 698, 324], "text": "52"}]}, {"boundingBox": [952, 304, 995, 305, 996, 322, 952, 322], "text": "79.99", "words": [{"boundingBox": [956, 303, 995, 303, 994, 321, 956, 321], "text": "79.99"}]}, {"boundingBox": [640, 341, 968, 342, 967, 362, 639, 361], "text": "2 Hose von delmod. DIE KOMFORTABLE. Leicht,", "words": [{"boundingBox": [645, 342, 655, 342, 654, 361, 644, 361], "text": "2"}, {"boundingBox": [659, 342, 696, 343, 695, 362, 658, 361], "text": "Hose"}, {"boundingBox": [700, 343, 728, 344, 727, 362, 699, 362], "text": "von"}, {"boundingBox": [731, 344, 787, 344, 787, 362, 731, 362], "text": "delmod."}, {"boundingBox": [791, 344, 814, 344, 814, 362, 791, 362], "text": "DIE"}, {"boundingBox": [818, 344, 919, 344, 918, 362, 818, 362], "text": "KOMFORTABLE."}, {"boundingBox": [922, 344, 968, 343, 968, 362, 922, 362], "text": "Leicht,"}]}, {"boundingBox": [642, 363, 986, 362, 987, 381, 643, 382], "text": "weich und mit einem farbintensiven Bluten-Dessin,", "words": [{"boundingBox": [643, 364, 682, 364, 683, 382, 643, 382], "text": "weich"}, {"boundingBox": [686, 364, 713, 364, 713, 382, 686, 382], "text": "und"}, {"boundingBox": [717, 364, 739, 364, 739, 382, 717, 382], "text": "mit"}, {"boundingBox": [743, 364, 785, 364, 785, 381, 743, 381], "text": "einem"}, {"boundingBox": [791, 364, 887, 364, 887, 382, 791, 381], "text": "farbintensiven"}, {"boundingBox": [890, 364, 987, 363, 986, 383, 890, 382], "text": "Bluten-Dessin,"}]}, {"boundingBox": [637, 384, 967, 382, 968, 400, 638, 402], "text": "so zeigt sich diese Baumwoll-Hose. In 5-Pocket-", "words": [{"boundingBox": [643, 385, 659, 385, 659, 402, 643, 403], "text": "so"}, {"boundingBox": [662, 385, 696, 384, 696, 402, 663, 402], "text": "zeigt"}, {"boundingBox": [700, 384, 730, 384, 730, 402, 700, 402], "text": "sich"}, {"boundingBox": [734, 384, 769, 384, 769, 402, 734, 402], "text": "diese"}, {"boundingBox": [773, 384, 880, 383, 881, 401, 773, 402], "text": "Baumwoll-Hose."}, {"boundingBox": [884, 383, 899, 383, 899, 401, 884, 401], "text": "In"}, {"boundingBox": [902, 383, 967, 383, 968, 401, 903, 401], "text": "5-Pocket-"}]}, {"boundingBox": [641, 403, 982, 402, 983, 421, 642, 422], "text": "Form, mit verkurzter Knochellange und schmalem", "words": [{"boundingBox": [642, 404, 680, 404, 680, 422, 642, 422], "text": "Form,"}, {"boundingBox": [684, 404, 705, 404, 705, 422, 683, 422], "text": "mit"}, {"boundingBox": [709, 404, 776, 404, 776, 422, 709, 422], "text": "verkurzter"}, {"boundingBox": [780, 404, 874, 404, 874, 422, 779, 422], "text": "Knochellange"}, {"boundingBox": [878, 404, 905, 404, 905, 422, 878, 422], "text": "und"}, {"boundingBox": [909, 404, 978, 403, 978, 423, 909, 422], "text": "schmalem"}]}, {"boundingBox": [642, 423, 977, 424, 976, 442, 641, 440], "text": "Bein. FuBweite ca. 30 cm. Innenbeinlange ca. 68", "words": [{"boundingBox": [643, 423, 676, 424, 676, 441, 643, 441], "text": "Bein."}, {"boundingBox": [679, 424, 741, 424, 741, 441, 680, 441], "text": "FuBweite"}, {"boundingBox": [744, 424, 765, 424, 766, 441, 745, 441], "text": "ca."}, {"boundingBox": [769, 424, 788, 424, 788, 441, 770, 441], "text": "30"}, {"boundingBox": [791, 424, 815, 424, 815, 441, 792, 441], "text": "cm."}, {"boundingBox": [818, 424, 927, 425, 927, 442, 819, 441], "text": "Innenbeinlange"}, {"boundingBox": [930, 425, 951, 425, 952, 442, 931, 442], "text": "ca."}, {"boundingBox": [955, 425, 976, 425, 977, 442, 956, 442], "text": "68"}]}, {"boundingBox": [644, 443, 987, 444, 987, 463, 643, 462], "text": "cm, in KurzgroBen ca. 62 cm. 97% Baumwolle, 3%", "words": [{"boundingBox": [644, 445, 666, 445, 666, 461, 644, 461], "text": "cm,"}, {"boundingBox": [670, 445, 684, 445, 684, 461, 670, 461], "text": "in"}, {"boundingBox": [687, 444, 766, 444, 766, 461, 687, 461], "text": "KurzgroBen"}, {"boundingBox": [769, 444, 789, 444, 790, 461, 769, 461], "text": "ca."}, {"boundingBox": [793, 444, 812, 444, 813, 461, 793, 461], "text": "62"}, {"boundingBox": [815, 444, 841, 444, 842, 461, 816, 461], "text": "cm."}, {"boundingBox": [844, 444, 877, 444, 878, 462, 845, 461], "text": "97%"}, {"boundingBox": [880, 444, 961, 444, 962, 463, 881, 462], "text": "Baumwolle,"}, {"boundingBox": [964, 444, 984, 444, 986, 463, 965, 463], "text": "3%"}]}, {"boundingBox": [639, 461, 840, 462, 839, 482, 638, 480], "text": "Elasthan. Maschinenwasche.", "words": [{"boundingBox": [642, 461, 703, 463, 704, 481, 643, 481], "text": "Elasthan."}, {"boundingBox": [707, 463, 839, 463, 839, 481, 708, 481], "text": "Maschinenwasche."}]}, {"boundingBox": [638, 485, 850, 487, 849, 507, 637, 505], "text": "24 801/306 ecru-multicolor", "words": [{"boundingBox": [643, 486, 667, 487, 667, 506, 643, 506], "text": "24"}, {"boundingBox": [671, 487, 743, 487, 744, 506, 671, 506], "text": "801/306"}, {"boundingBox": [747, 487, 849, 488, 850, 507, 748, 506], "text": "ecru-multicolor"}]}, {"boundingBox": [640, 511, 747, 512, 746, 532, 639, 531], "text": "19, 20, 38, 40", "words": [{"boundingBox": [644, 512, 666, 512, 666, 532, 644, 532], "text": "19,"}, {"boundingBox": [670, 512, 694, 512, 694, 532, 670, 532], "text": "20,"}, {"boundingBox": [697, 512, 721, 512, 721, 532, 698, 532], "text": "38,"}, {"boundingBox": [725, 512, 747, 513, 747, 533, 725, 532], "text": "40"}]}, {"boundingBox": [949, 512, 999, 514, 998, 531, 948, 530], "text": "99.99", "words": [{"boundingBox": [954, 514, 998, 514, 999, 531, 955, 531], "text": "99.99"}]}, {"boundingBox": [641, 531, 798, 532, 797, 552, 640, 551], "text": "21, 22, 23, 42, 44, 46", "words": [{"boundingBox": [644, 532, 666, 532, 667, 551, 644, 552], "text": "21,"}, {"boundingBox": [670, 532, 693, 532, 693, 551, 670, 551], "text": "22,"}, {"boundingBox": [697, 532, 721, 532, 720, 551, 697, 551], "text": "23,"}, {"boundingBox": [724, 532, 747, 532, 747, 551, 724, 551], "text": "42,"}, {"boundingBox": [751, 532, 775, 533, 774, 551, 751, 551], "text": "44,"}, {"boundingBox": [779, 533, 797, 533, 796, 552, 778, 551], "text": "46"}]}, {"boundingBox": [944, 530, 995, 529, 996, 547, 945, 549], "text": "109.99", "words": [{"boundingBox": [945, 532, 996, 531, 995, 549, 946, 549], "text": "109.99"}]}, {"boundingBox": [640, 552, 770, 553, 769, 572, 639, 571], "text": "24, 25, 48, 50, 52", "words": [{"boundingBox": [644, 552, 665, 553, 666, 572, 644, 571], "text": "24,"}, {"boundingBox": [669, 553, 694, 553, 694, 572, 670, 572], "text": "25,"}, {"boundingBox": [697, 553, 720, 554, 721, 572, 698, 572], "text": "48,"}, {"boundingBox": [724, 554, 746, 555, 747, 572, 725, 572], "text": "50,"}, {"boundingBox": [750, 555, 769, 555, 770, 571, 750, 572], "text": "52"}]}, {"boundingBox": [945, 553, 995, 551, 997, 570, 945, 570], "text": "119.99", "words": [{"boundingBox": [945, 551, 996, 550, 996, 569, 946, 570], "text": "119.99"}]}, {"boundingBox": [641, 588, 971, 591, 970, 610, 640, 608], "text": "3 Hemdbluse von delmod. Reizvoll-feminin gibt", "words": [{"boundingBox": [644, 589, 654, 589, 656, 608, 645, 608], "text": "3"}, {"boundingBox": [658, 589, 739, 591, 740, 609, 659, 609], "text": "Hemdbluse"}, {"boundingBox": [743, 591, 772, 591, 772, 609, 744, 609], "text": "von"}, {"boundingBox": [775, 591, 831, 592, 832, 610, 776, 609], "text": "delmod."}, {"boundingBox": [835, 592, 943, 591, 944, 610, 836, 610], "text": "Reizvoll-feminin"}, {"boundingBox": [947, 591, 971, 591, 971, 610, 948, 610], "text": "gibt", "confidence": "Low"}]}, {"boundingBox": [638, 610, 984, 612, 983, 629, 637, 628], "text": "sich diese stretchbequeme Bluse mit aufwandiger", "words": [{"boundingBox": [642, 611, 673, 611, 673, 628, 643, 628], "text": "sich"}, {"boundingBox": [677, 611, 712, 611, 713, 628, 678, 628], "text": "diese"}, {"boundingBox": [716, 612, 826, 612, 827, 629, 716, 628], "text": "stretchbequeme"}, {"boundingBox": [830, 612, 867, 612, 868, 629, 831, 629], "text": "Bluse"}, {"boundingBox": [870, 612, 894, 612, 895, 629, 872, 629], "text": "mit"}, {"boundingBox": [897, 612, 982, 612, 984, 630, 898, 629], "text": "aufwandiger"}]}, {"boundingBox": [638, 630, 986, 632, 986, 650, 637, 648], "text": "Blumen-Stickerei am Kragen. Mit langen Manschet", "words": [{"boundingBox": [642, 632, 757, 633, 757, 648, 643, 648], "text": "Blumen-Stickerei"}, {"boundingBox": [760, 633, 779, 633, 780, 649, 760, 648], "text": "am"}, {"boundingBox": [787, 633, 838, 633, 838, 649, 787, 649], "text": "Kragen."}, {"boundingBox": [841, 633, 863, 633, 863, 649, 841, 649], "text": "Mit"}, {"boundingBox": [867, 633, 915, 633, 915, 649, 866, 649], "text": "langen"}, {"boundingBox": [919, 633, 987, 632, 986, 650, 918, 649], "text": "Manschet", "confidence": "Low"}]}, {"boundingBox": [641, 649, 987, 650, 986, 668, 640, 667], "text": "tenarmeln und Passformnahten im Rucken. Lange", "words": [{"boundingBox": [642, 651, 713, 650, 713, 668, 643, 668], "text": "tenarmeln"}, {"boundingBox": [716, 650, 743, 650, 743, 668, 717, 668], "text": "und"}, {"boundingBox": [746, 650, 858, 650, 858, 668, 747, 668], "text": "Passformnahten"}, {"boundingBox": [861, 650, 876, 650, 876, 668, 861, 668], "text": "im"}, {"boundingBox": [882, 650, 936, 651, 936, 668, 883, 668], "text": "Rucken."}, {"boundingBox": [939, 651, 985, 651, 985, 668, 939, 668], "text": "Lange"}]}, {"boundingBox": [623, 668, 988, 667, 989, 690, 624, 690], "text": "in Gr. 38 ca. 66 cm. 96% Baumwolle, 4% Elasthan.", "words": [{"boundingBox": [641, 670, 656, 670, 656, 689, 641, 689], "text": "in"}, {"boundingBox": [659, 670, 679, 670, 679, 689, 660, 689], "text": "Gr."}, {"boundingBox": [683, 670, 701, 669, 701, 689, 683, 689], "text": "38"}, {"boundingBox": [705, 669, 725, 669, 726, 688, 705, 689], "text": "ca."}, {"boundingBox": [729, 669, 747, 669, 748, 688, 729, 688], "text": "66"}, {"boundingBox": [751, 669, 777, 668, 777, 688, 751, 688], "text": "cm."}, {"boundingBox": [780, 668, 812, 668, 812, 688, 781, 688], "text": "96%"}, {"boundingBox": [816, 668, 895, 668, 896, 689, 816, 688], "text": "Baumwolle,"}, {"boundingBox": [899, 669, 921, 669, 921, 689, 899, 689], "text": "4%"}, {"boundingBox": [925, 669, 988, 670, 989, 690, 925, 689], "text": "Elasthan."}]}, {"boundingBox": [41, 693, 57, 691, 58, 709, 42, 711], "text": "2", "words": [{"boundingBox": [41, 692, 53, 691, 56, 709, 44, 710], "text": "2"}]}, {"boundingBox": [39, 702, 124, 707, 123, 730, 37, 725], "text": "Hose, ab", "words": [{"boundingBox": [40, 705, 93, 706, 93, 728, 41, 726], "text": "Hose,"}, {"boundingBox": [97, 706, 121, 707, 121, 730, 97, 728], "text": "ab"}]}, {"boundingBox": [641, 688, 775, 692, 774, 710, 640, 707], "text": "Maschinenwasche.", "words": [{"boundingBox": [642, 690, 774, 693, 774, 710, 642, 708], "text": "Maschinenwasche."}]}, {"boundingBox": [39, 727, 131, 724, 133, 759, 41, 768], "text": "99,99", "words": [{"boundingBox": [43, 726, 128, 721, 130, 762, 46, 767], "text": "99,99", "confidence": "Low"}]}, {"boundingBox": [642, 713, 802, 714, 801, 733, 641, 732], "text": "24 799/506 offwhite", "words": [{"boundingBox": [644, 714, 667, 714, 667, 733, 644, 733], "text": "24"}, {"boundingBox": [672, 714, 744, 715, 745, 734, 672, 733], "text": "799/506"}, {"boundingBox": [748, 715, 800, 715, 802, 734, 749, 734], "text": "offwhite"}]}, {"boundingBox": [639, 738, 690, 740, 689, 756, 638, 754], "text": "38, 40", "words": [{"boundingBox": [644, 739, 667, 740, 668, 755, 645, 755], "text": "38,"}, {"boundingBox": [670, 740, 689, 740, 689, 756, 671, 755], "text": "40"}]}, {"boundingBox": [953, 740, 998, 738, 998, 756, 954, 756], "text": "69.99", "words": [{"boundingBox": [954, 738, 996, 738, 997, 756, 955, 756], "text": "69.99"}]}, {"boundingBox": [644, 758, 716, 759, 715, 779, 643, 778], "text": "42, 44, 46", "words": [{"boundingBox": [644, 758, 667, 759, 666, 778, 644, 777], "text": "42,"}, {"boundingBox": [670, 760, 694, 760, 695, 779, 670, 778], "text": "44,"}, {"boundingBox": [698, 760, 716, 760, 716, 778, 698, 778], "text": "46"}]}, {"boundingBox": [950, 759, 996, 758, 996, 776, 951, 777], "text": "75.99", "words": [{"boundingBox": [955, 758, 995, 757, 995, 775, 955, 776], "text": "75.99", "confidence": "Low"}]}, {"boundingBox": [640, 778, 716, 781, 715, 799, 639, 797], "text": "48, 50, 52", "words": [{"boundingBox": [644, 780, 667, 781, 666, 798, 642, 797], "text": "48,"}, {"boundingBox": [671, 781, 694, 782, 693, 799, 670, 799], "text": "50,"}, {"boundingBox": [697, 782, 716, 782, 716, 800, 697, 799], "text": "52"}]}, {"boundingBox": [954, 783, 999, 781, 1000, 797, 954, 799], "text": "79.99", "words": [{"boundingBox": [955, 781, 998, 780, 999, 797, 956, 798], "text": "79.99"}]}, {"boundingBox": [52, 807, 87, 805, 87, 819, 52, 821], "text": "KURZEN", "words": [{"boundingBox": [52, 806, 85, 805, 86, 819, 52, 820], "text": "KURZEN", "confidence": "Low"}]}, {"boundingBox": [56, 826, 88, 826, 87, 854, 56, 854], "text": "K", "words": [{"boundingBox": [59, 826, 78, 826, 78, 854, 59, 854], "text": "K"}]}, {"boundingBox": [46, 861, 93, 859, 94, 873, 47, 874], "text": "GROSSEN", "words": [{"boundingBox": [48, 861, 94, 860, 94, 874, 48, 875], "text": "GROSSEN"}]}, {"boundingBox": [961, 910, 980, 910, 980, 928, 961, 928], "text": "3", "words": [{"boundingBox": [963, 910, 976, 910, 976, 928, 963, 928], "text": "3"}]}, {"boundingBox": [962, 923, 1100, 925, 1099, 948, 961, 946], "text": "Hemdbluse, ab", "words": [{"boundingBox": [962, 924, 1071, 926, 1071, 948, 963, 945], "text": "Hemdbluse,"}, {"boundingBox": [1075, 926, 1100, 925, 1100, 947, 1075, 948], "text": "ab"}]}, {"boundingBox": [962, 953, 1050, 949, 1051, 977, 962, 988], "text": "69.99", "words": [{"boundingBox": [963, 952, 1049, 945, 1052, 979, 966, 986], "text": "69.99", "confidence": "Low"}]}, {"boundingBox": [40, 1534, 66, 1529, 69, 1548, 43, 1552], "text": "80", "words": [{"boundingBox": [42, 1532, 64, 1528, 67, 1547, 45, 1551], "text": "80"}]}]}}